Staticfy-1.3.dist-info/DESCRIPTION.rst
Staticfy-1.3.dist-info/METADATA
Staticfy-1.3.dist-info/RECORD
Staticfy-1.3.dist-info/WHEEL
Staticfy-1.3.dist-info/entry_points.txt
Staticfy-1.3.dist-info/metadata.json
Staticfy-1.3.dist-info/top_level.txt
staticfy/__config__.py
staticfy/__init__.py
staticfy/__main__.py
staticfy/staticfy.py
