Metadata-Version: 2.0
Name: Staticfy
Version: 1.3
Summary: Convert static assets links to dynamic web framework links
Home-page: https://github.com/danidee10/Staticfy
Author: Osaetin Daniel
Author-email: osaetindaniel@gmail.com
License: GPL
Platform: UNKNOWN
Requires-Dist: beautifulsoup4
